landfall/__init__.py
landfall/color.py
landfall/colorsys.py
landfall/combos.py
landfall/context.py
landfall/distinctipy.py
landfall/plot.py
landfall/points.py
landfall/polygons.py
landfall-0.3.5.dist-info/LICENSE
landfall-0.3.5.dist-info/METADATA
landfall-0.3.5.dist-info/WHEEL
landfall-0.3.5.dist-info/top_level.txt
landfall-0.3.5.dist-info/RECORD
